elexon/__init__.py
elexon/__main__.py
elexon/elexon.py
elexon/exceptions.py
elexon/methods.py
elexon/parsers.py
tests/__init__.py
tests/test_elexon.py
tests/test_exceptions.py
tests/test_methods.py
tests/test_parsers.py
elexon-0.2.3.dist-info/LICENSE
elexon-0.2.3.dist-info/METADATA
elexon-0.2.3.dist-info/WHEEL
elexon-0.2.3.dist-info/entry_points.txt
elexon-0.2.3.dist-info/top_level.txt
elexon-0.2.3.dist-info/RECORD
