Metadata-Version: 2.1
Name: elexon
Version: 0.2.3
Summary: A simple wrapper for the Elexon BMRS API
Home-page: https://github.com/MichaelKavanagh/elexon
Author: Michael Kavanagh
License: UNKNOWN
Platform: UNKNOWN
Classifier: Development Status :: 2 - Pre-Alpha
Classifier: Programming Language :: Python :: 3
Classifier: License :: OSI Approved :: MIT License
Classifier: Operating System :: OS Independent
Requires-Python: >=3.6
License-File: LICENSE
Requires-Dist: requests
